winsign/__init__.py
winsign/asn1.py
winsign/cli.py
winsign/crypto.py
winsign/makemsix.py
winsign/osslsigncode.py
winsign/pefile.py
winsign/sign.py
winsign/timestamp.py
winsign/verify.py
winsign-2.2.4.dist-info/METADATA
winsign-2.2.4.dist-info/WHEEL
winsign-2.2.4.dist-info/entry_points.txt
winsign-2.2.4.dist-info/top_level.txt
winsign-2.2.4.dist-info/RECORD
