Metadata-Version: 2.1
Name: winsign
Version: 2.2.4
Summary: Utilities to support code signing Windows executable files
Home-page: https://github.com/mozilla/winsign
Author: Joel Maher
Author-email: jmaher@mozilla.com
License: MPL2.0
Keywords: winsign
Platform: UNKNOWN
Classifier: Development Status :: 2 - Pre-Alpha
Classifier: Intended Audience :: Developers
Classifier: License :: OSI Approved :: Mozilla Public License 2.0 (MPL 2.0)
Classifier: Natural Language :: English
Classifier: Programming Language :: Python :: 3
Classifier: Programming Language :: Python :: 3.8
Classifier: Programming Language :: Python :: 3.9
Requires-Dist: construct
Requires-Dist: cryptography
Requires-Dist: pyasn1
Requires-Dist: pyasn1-modules (>=0.2.6)
